Surya_indian_search_engine/__init__.py
Surya_indian_search_engine/__main__.py
Surya_indian_search_engine/main.py
Surya_indian_search_engine-1.dist-info/METADATA
Surya_indian_search_engine-1.dist-info/WHEEL
Surya_indian_search_engine-1.dist-info/top_level.txt
Surya_indian_search_engine-1.dist-info/RECORD
